ykpivfs/__init__.py
ykpivfs/cli.py
ykpivfs/fs.py
ykpivfs/fuse.py
ykpivfs/io.py
yubikey_pivfs-0.0.7.dist-info/LICENSE
yubikey_pivfs-0.0.7.dist-info/METADATA
yubikey_pivfs-0.0.7.dist-info/WHEEL
yubikey_pivfs-0.0.7.dist-info/entry_points.txt
yubikey_pivfs-0.0.7.dist-info/top_level.txt
yubikey_pivfs-0.0.7.dist-info/RECORD
