Metadata-Version: 2.1
Name: yubikey-pivfs
Version: 0.0.7
Summary: A FUSE filesystem for YubiKey PIV
Home-page: https://github.com/RazzM13/yubikey-pivfs
Author: RazzM13
License: UNKNOWN
Project-URL: Bug Tracker, https://github.com/RazzM13/yubikey-pivfs/issues
Platform: UNKNOWN
Classifier: Programming Language :: Python :: 3
Classifier: License :: OSI Approved :: MIT License
Classifier: Operating System :: OS Independent
Requires-Python: >=3.6
License-File: LICENSE
Requires-Dist: fs
Requires-Dist: zstd
Requires-Dist: PyNaCL
Requires-Dist: fusepy
Requires-Dist: yubikey-manager
